keycardai/oauth/__init__.py
keycardai/oauth/client.py
keycardai/oauth/exceptions.py
keycardai/oauth/http/__init__.py
keycardai/oauth/http/_context.py
keycardai/oauth/http/_transports.py
keycardai/oauth/http/_wire.py
keycardai/oauth/http/auth.py
keycardai/oauth/http/transport.py
keycardai/oauth/operations/_discovery.py
keycardai/oauth/operations/_registration.py
keycardai/oauth/operations/_token_exchange.py
keycardai/oauth/types/__init__.py
keycardai/oauth/types/models.py
keycardai/oauth/types/oauth.py
keycardai/oauth/utils/__init__.py
keycardai/oauth/utils/bearer.py
keycardai/oauth/utils/crypto.py
keycardai/oauth/utils/jwt.py
keycardai/oauth/utils/pkce.py
keycardai_oauth-0.6.0.dist-info/METADATA
keycardai_oauth-0.6.0.dist-info/WHEEL
keycardai_oauth-0.6.0.dist-info/RECORD
